README.md
setup.py
compute_rhino3d/AreaMassProperties.py
compute_rhino3d/BezierCurve.py
compute_rhino3d/Brep.py
compute_rhino3d/BrepFace.py
compute_rhino3d/Curve.py
compute_rhino3d/Extrusion.py
compute_rhino3d/GeometryBase.py
compute_rhino3d/Grasshopper.py
compute_rhino3d/Intersection.py
compute_rhino3d/Mesh.py
compute_rhino3d/NurbsCurve.py
compute_rhino3d/NurbsSurface.py
compute_rhino3d/SubD.py
compute_rhino3d/Surface.py
compute_rhino3d/Util.py
compute_rhino3d/VolumeMassProperties.py
compute_rhino3d/__init__.py
compute_rhino3d.egg-info/PKG-INFO
compute_rhino3d.egg-info/SOURCES.txt
compute_rhino3d.egg-info/dependency_links.txt
compute_rhino3d.egg-info/requires.txt
compute_rhino3d.egg-info/top_level.txt