Metadata-Version: 2.1
Name: compute-rhino3d
Version: 0.12.2
Summary: Python client library for compute.rhino3d web service
Home-page: https://github.com/mcneel/compute.rhino3d
Author: Robert McNeel & Associates
Author-email: steve@mcneel.com
License: UNKNOWN
Platform: UNKNOWN
Classifier: Development Status :: 4 - Beta
Classifier: Intended Audience :: Developers
Classifier: License :: OSI Approved :: MIT License
Classifier: Programming Language :: Python
